CHANGELOG
LICENSE
MANIFEST.in
README
VERSION
extras_requirements.txt
requirements.txt
setup.py
src/causal/__init__.py
src/causal/local_settings.py
src/causal/manage.py
src/causal/settings.py
src/causal/urls.py
src/causal/version.txt
src/causal/wingdbstub.py
src/causal.egg-info/PKG-INFO
src/causal.egg-info/SOURCES.txt
src/causal.egg-info/dependency_links.txt
src/causal.egg-info/requires.txt
src/causal.egg-info/top_level.txt
src/causal/delicious/__init__.py
src/causal/delicious/models.py
src/causal/delicious/service.py
src/causal/delicious/tests.py
src/causal/delicious/urls.py
src/causal/delicious/views.py
src/causal/delicious/templates/causal/delicious/stats.html
src/causal/delicious/test_data/unknown_user.json
src/causal/delicious/test_data/user_feed.json
src/causal/facebook/__init__.py
src/causal/facebook/models.py
src/causal/facebook/service.py
src/causal/facebook/tests.py
src/causal/facebook/urls.py
src/causal/facebook/views.py
src/causal/facebook/templates/causal/facebook/stats.html
src/causal/flickr/__init__.py
src/causal/flickr/models.py
src/causal/flickr/service.py
src/causal/flickr/tests.py
src/causal/flickr/urls.py
src/causal/flickr/views.py
src/causal/flickr/templates/causal/flickr/stats.html
src/causal/foursquare/__init__.py
src/causal/foursquare/models.py
src/causal/foursquare/service.py
src/causal/foursquare/tests.py
src/causal/foursquare/urls.py
src/causal/foursquare/views.py
src/causal/foursquare/templates/causal/foursquare/stats.html
src/causal/foursquare/test_data/badges.json
src/causal/foursquare/test_data/checkins.json
src/causal/github/__init__.py
src/causal/github/models.py
src/causal/github/service.py
src/causal/github/tests.py
src/causal/github/urls.py
src/causal/github/views.py
src/causal/github/fixtures/user_services.json
src/causal/github/fixtures/users.json
src/causal/github/fixtures/uservice_app.json
src/causal/github/templates/causal/github/stats.html
src/causal/github/test_data/user_feed.json
src/causal/googlereader/__init__.py
src/causal/googlereader/models.py
src/causal/googlereader/service.py
src/causal/googlereader/tests.py
src/causal/googlereader/urls.py
src/causal/googlereader/views.py
