Metadata-Version: 1.0
Name: causal
Version: 1.0.21
Summary: Open source lifestream aggregator
Home-page: http://www.projectcausal.com/
Author: Project Causal Team
Author-email: team@projectcausal.com
License: Apache License 2.0
Download-URL: https://github.com/causality/causal/tarball/1.0.21
Keywords: lifestream,aggregator,socialnetwork,django,social
Platform: UNKNOWN
Classifier: Development Status :: 4 - Beta
Classifier: Environment :: Web Environment
Classifier: Framework :: Django
Classifier: Intended Audience :: Developers
Classifier: Intended Audience :: End Users/Desktop
Classifier: License :: OSI Approved :: Apache Software License
Classifier: Topic :: Internet :: WWW/HTTP
